spotui/__init__.py
spotui/__main__.py
spotui/version.py
spotui/src/DeviceMenu.py
spotui/src/LibraryList.py
spotui/src/LibraryMenu.py
spotui/src/Logging.py
spotui/src/MainForm.py
spotui/src/NowPlaying.py
spotui/src/PlaylistMenu.py
spotui/src/SearchInput.py
spotui/src/TracksMenu.py
spotui/src/__init__.py
spotui/src/colors.py
spotui/src/component.py
spotui/src/config.py
spotui/src/input.py
spotui/src/menu.py
spotui/src/spotifyApi.py
spotui/src/ui.py
spotui/src/util.py
spotui-0.1.20.dist-info/LICENSE
spotui-0.1.20.dist-info/METADATA
spotui-0.1.20.dist-info/WHEEL
spotui-0.1.20.dist-info/entry_points.txt
spotui-0.1.20.dist-info/top_level.txt
spotui-0.1.20.dist-info/RECORD
