Metadata-Version: 2.1
Name: spotui
Version: 0.1.20
Summary: Spotify TUI
Home-page: https://github.com/ceuk/spotui
Author: ceuk
License: MIT
Keywords: spotify spotifytui
Classifier: Programming Language :: Python :: 3
Classifier: Programming Language :: Python :: 3.4
Classifier: Programming Language :: Python :: 3.5
Classifier: Programming Language :: Python :: 3.6
Classifier: Programming Language :: Python :: 3.7
Classifier: License :: OSI Approved :: MIT License
Requires-Python: >=3.4
License-File: LICENSE
Requires-Dist: spotipy (==2.7.1)
